RagAdhocQueryDoc.py
RagChromaDB.py
RagChunkText.py
RagEmbeddings.py
RagFaiss.py
RagLLM.py
RagPdf2Text.py
RagPrompt.py
__init__.py
elements/__init__.py
elements/document.py
elements/ollamaWrapper.py
elements/prompt.py
elements/chromadb/__init__.py
elements/chromadb/cdbWrapper.py
elements/embeddings/sentTransEmbsFactory.py
elements/faiss/FAISSWrapper.py
elements/faiss/__init__.py
rag/ragCL.py
rag/ragCLChromadb.py
rag/ragCLFaiss.py
utils/CONST.py
utils/FUNCTIONS.py
utils/__init__.py
utils/log.py
utils/milestone.py
RagCLI-0.1.1.2.dist-info/LICENSE
RagCLI-0.1.1.2.dist-info/METADATA
RagCLI-0.1.1.2.dist-info/WHEEL
RagCLI-0.1.1.2.dist-info/entry_points.txt
RagCLI-0.1.1.2.dist-info/top_level.txt
RagCLI-0.1.1.2.dist-info/RECORD
